{
    "type": "STRUCT_VARIANT_ARRAY",
    "params": {
        "VideoSlot": {
            "import": {"url": "include"},
            "type": "UNDEFINED"
        },
        "AudioSlot": {
            "import": {"url": "include"},
            "type": "UNDEFINED"
        }
    },
    "value": {
        "variant_array_values": {
            "variants": [
                {
                    "variant_type": "AudioSlot",
                    "value": {
                        "struct_value": {
                            "fields": {
                                "id": {
                                    "value": {"string_value": "audio1"}
                                },
                                "label": {
                                    "value": {"string_value": "Audio 1"}
                                },
                                "gain": {
                                    "value": {"float32_value": 0.5}
                                }
                            }
                        }
                    }
                },
                {
                    "variant_type": "VideoSlot",
                    "value": {
                        "struct_value": {
                            "fields": {
                                "id": {
                                    "value": {"string_value": "video1"}
                                },
                                "label": {
                                    "value": {"string_value": "Video 1"}
                                }
                            }
                        }
                    }
                }
            ]
        }
    }
}